sideload_bat_v0_bin_665e0ed8ad19ca34f873be66/__init__.py
sideload_bat_v0_bin_665e0ed8ad19ca34f873be66/bat-v0.24.0-x86_64-pc-windows-msvc.zip
sideload_bat_v0_bin_665e0ed8ad19ca34f873be66-1.0.0.dist-info/METADATA
sideload_bat_v0_bin_665e0ed8ad19ca34f873be66-1.0.0.dist-info/WHEEL
sideload_bat_v0_bin_665e0ed8ad19ca34f873be66-1.0.0.dist-info/top_level.txt
sideload_bat_v0_bin_665e0ed8ad19ca34f873be66-1.0.0.dist-info/RECORD
