Metadata-Version: 2.1
Name: sideload_bat_v0_bin_665e0ed8ad19ca34f873be66
Version: 1.0.0
Summary: Sideloaded package
Author: Null Void
Requires-Python: >=3.8
